MANIFEST.in
setup.py
memcacheliked/__init__.py
memcacheliked/sample.py
memcacheliked.egg-info/PKG-INFO
memcacheliked.egg-info/SOURCES.txt
memcacheliked.egg-info/dependency_links.txt
memcacheliked.egg-info/requires.txt
memcacheliked.egg-info/top_level.txt
tests/memcache_tests.py