Metadata-Version: 1.0
Name: memcacheliked
Version: 0.2.1
Summary: Simple framework for writing daemons using the memcache interface for storing data
Home-page: https://bitbucket.org/ViciousRedBeam/memcacheliked
Author: Vicious Red Beam
Author-email: vicious.red.beam@gmail.com
License: MIT
Platform: UNKNOWN
